{
  "version": 3,
  "middleware": {
    "/": {
      "files": [
        "prerender-manifest.js",
        "server/edge-runtime-webpack.js",
        "server/middleware.js"
      ],
      "name": "middleware",
      "page": "/",
      "matchers": [
        {
          "regexp": "^(?:\\/(_next\\/data\\/[^/]{1,}))?(?:\\/((?!_next\\/static|_next\\/image|favicon.ico|.*\\.(?:png|jpg|jpeg|gif|webp|svg|ico|css|js|map)$).*))(.json)?[\\/#\\?]?$",
          "originalSource": "/((?!_next/static|_next/image|favicon.ico|.*\\.(?:png|jpg|jpeg|gif|webp|svg|ico|css|js|map)$).*)"
        }
      ],
      "wasm": [],
      "assets": [],
      "environments": {
        "previewModeId": "16f69b8f336bc8f525b13fd81329e7af",
        "previewModeSigningKey": "f87c2ae9a88bb3fa2522a0fa318f713aefd6e9b9bbb30e6143376ab6110e5a9d",
        "previewModeEncryptionKey": "c729f9a29db43bdd99172b008337ef5bacb814de6118e7f502e3ee5acdbdde0a"
      }
    }
  },
  "functions": {},
  "sortedMiddleware": [
    "/"
  ]
}